README.md
setup.cfg
setup.py
fluxx/__init__.py
fluxx/cli.py
fluxx/core.py
fluxx_wrapper.egg-info/PKG-INFO
fluxx_wrapper.egg-info/SOURCES.txt
fluxx_wrapper.egg-info/dependency_links.txt
fluxx_wrapper.egg-info/entry_points.txt
fluxx_wrapper.egg-info/requires.txt
fluxx_wrapper.egg-info/top_level.txt