Metadata-Version: 1.2
Name: fluxx-wrapper
Version: 0.0.6
Summary: A simple wrapper around Fluxx GMS's REST API.
Home-page: https://github.com/condad/fluxx-python-sdk
Author: Connor Sullivan
Author-email: sully4792@gmail.com
License: UNKNOWN
Download-URL: https://github.com/condad/fluxx-python-sdk/tarball/0.0.6
Keywords: fluxx,gms,api,wrapper
Platform: UNKNOWN
Classifier: Development Status :: 3 - Alpha
Classifier: Intended Audience :: Developers
Classifier: License :: OSI Approved :: Apache Software License
Classifier: Operating System :: OS Independent
Classifier: Programming Language :: Python
Classifier: Programming Language :: Python :: 3.5
Classifier: Programming Language :: Python :: 3.6
Classifier: Topic :: Software Development :: Libraries :: Python Modules
Requires-Python: >=3
